{"Systemy operacyjne": {"oceny": [], "nieobecnosci": 0, "max_nieobecnosci": 2}, "Projektowanie interfejs\u00f3w": {"oceny": [], "nieobecnosci": 0, "max_nieobecnosci": 2}, "Paradygmaty programowania": {"oceny": [], "nieobecnosci": 0, "max_nieobecnosci": 1}, "Technologie obiektowe i komponentowe": {"oceny": [], "nieobecnosci": 0, "max_nieobecnosci": 2}, "In\u017cynieria oprogramowania": {"oceny": [], "nieobecnosci": 0, "max_nieobecnosci": 1}, "Programowanie system\u00f3w mobilnych": {"oceny": [5, 5, 5], "nieobecnosci": 0, "max_nieobecnosci": 1}, "Bazy danych": {"oceny": [], "nieobecnosci": 0, "max_nieobecnosci": 2}, "Angielski": {"oceny": [], "nieobecnosci": 1, "max_nieobecnosci": 4}}